example_pkg/__init__.py
hfs_felixolivier-0.1.dist-info/LICENSE
hfs_felixolivier-0.1.dist-info/METADATA
hfs_felixolivier-0.1.dist-info/WHEEL
hfs_felixolivier-0.1.dist-info/top_level.txt
hfs_felixolivier-0.1.dist-info/RECORD
