Metadata-Version: 2.1
Name: hfs-felixolivier
Version: 0.1
Summary: initial test
Home-page: https://github.com/javatechy/dokr
Author: Felix van Deelen
Author-email: felixvandeelen@hotmail.com
License: UNKNOWN
Platform: UNKNOWN
Classifier: Programming Language :: Python :: 3
Classifier: License :: OSI Approved :: MIT License
Classifier: Operating System :: OS Independent
